audiolibrix/__init__.py
audiolibrix/error.py
audiolibrix/http_client.py
audiolibrix/resource.py
audiolibrix/version.py
audiolibrix-0.3.4.dist-info/LICENSE
audiolibrix-0.3.4.dist-info/METADATA
audiolibrix-0.3.4.dist-info/WHEEL
audiolibrix-0.3.4.dist-info/top_level.txt
audiolibrix-0.3.4.dist-info/RECORD
