Metadata-Version: 2.1
Name: audiolibrix
Version: 0.3.4
Summary: Audiolibrix Service Bindings for Python
Home-page: UNKNOWN
Author: Palo Sopko
Author-email: pavol@sopko.sk
License: MIT
Project-URL: Bug Tracker, https://github.com/palosopko/audiolibrix-python/issues
Project-URL: Source Code, https://github.com/palosopko/audiolibrix-python
Keywords: audiolibrix
Platform: UNKNOWN
Classifier: Development Status :: 5 - Production/Stable
Classifier: Intended Audience :: Developers
Classifier: License :: OSI Approved :: MIT License
Classifier: Operating System :: OS Independent
Classifier: Programming Language :: Python
Classifier: Programming Language :: Python :: 3
Classifier: Programming Language :: Python :: 3.6
Classifier: Programming Language :: Python :: 3.7
Classifier: Programming Language :: Python :: 3.8
Classifier: Programming Language :: Python :: 3.9
Classifier: Programming Language :: Python :: Implementation :: PyPy
Classifier: Topic :: Software Development :: Libraries :: Python Modules
Requires-Python: >=3.6.*
Requires-Dist: requests (>=2.21.0)
